wxgl/__init__.py
wxgl/app.py
wxgl/color.py
wxgl/glutfigure.py
wxgl/imgres.py
wxgl/light.py
wxgl/model.py
wxgl/pointcloud.py
wxgl/qtapp.py
wxgl/qtfigure.py
wxgl/qtscene.py
wxgl/scene.py
wxgl/scheme.py
wxgl/scheme的副本.py
wxgl/text.py
wxgl/texture.py
wxgl/util.py
wxgl/wxapp.py
wxgl/wxfigure.py
wxgl/wxscene.py
wxgl-0.9.14.dist-info/METADATA
wxgl-0.9.14.dist-info/WHEEL
wxgl-0.9.14.dist-info/top_level.txt
wxgl-0.9.14.dist-info/RECORD
