Metadata-Version: 2.1
Name: wxgl
Version: 0.9.14
Summary: A 3d library based pyOpenGL.
Home-page: https://github.com/xufive/wxgl
Author: xufive
Author-email: xufive@gmail.com
Classifier: Programming Language :: Python :: 3
Classifier: License :: OSI Approved :: MIT License
Classifier: Operating System :: OS Independent
Requires-Dist: pyopengl (>=3.1.5)
Requires-Dist: numpy (>=1.20.2)
Requires-Dist: matplotlib (>=3.1.2)
Requires-Dist: pyqt6 (>=6.3.0)
Requires-Dist: pillow (>=8.2.0)
Requires-Dist: freetype-py (>=2.3.0)
Requires-Dist: imageio (>=2.22.0)
Requires-Dist: imageio-ffmpeg (>=0.4.8)
Requires-Dist: webp (>=0.1.5)
